{"stockData":[{"stockID":1,"stock":{"industry":"Packaged Foods","sector":"Consumer Non-Durables","symbol":"MKC","name":"McCormick & Company, Incorporated"},"rates":{"buy":232.24,"sell":227.17,"timestamp":"2020-02-06 13:36:47"}},
{"stockID":2,"stock":{"industry":"n/a","sector":"n/a","symbol":"INFR","name":"Legg Mason Global Infrastructure ETF"},"rates":{"buy":163.72,"sell":261.39,"timestamp":"2020-05-02 02:16:49"}},
{"stockID":3,"stock":{"industry":"n/a","sector":"n/a","symbol":"MIY","name":"Blackrock MuniYield Michigan Quality Fund, Inc."},"rates":{"buy":174.96,"sell":175.98,"timestamp":"2021-04-19 03:25:35"}},
{"stockID":4,"stock":{"industry":"Specialty Insurers","sector":"Finance","symbol":"MMC","name":"Marsh & McLennan Companies, Inc."},"rates":{"buy":249.95,"sell":147.45,"timestamp":"2019-03-22 14:31:02"}},
{"stockID":5,"stock":{"industry":"n/a","sector":"n/a","symbol":"FEX","name":"First Trust Large Cap Core AlphaDEX Fund"},"rates":{"buy":133.02,"sell":133.65,"timestamp":"2019-04-17 22:07:29"}},
{"stockID":6,"stock":{"industry":"Packaged Foods","sector":"Consumer Non-Durables","symbol":"MDLZ","name":"Mondelez International, Inc."},"rates":{"buy":103.22,"sell":173.32,"timestamp":"2019-06-14 23:21:19"}},
{"stockID":7,"stock":{"industry":"Building operators","sector":"Consumer Services","symbol":"PDM","name":"Piedmont Office Realty Trust, Inc."},"rates":{"buy":155.19,"sell":168.76,"timestamp":"2018-10-15 09:24:06"}},
{"stockID":8,"stock":{"industry":"Medical/Nursing Services","sector":"Health Care","symbol":"KANG","name":"iKang Healthcare Group, Inc."},"rates":{"buy":237.14,"sell":247.85,"timestamp":"2020-04-11 15:39:07"}},
{"stockID":9,"stock":{"industry":"Property-Casualty Insurers","sector":"Finance","symbol":"SIGI","name":"Selective Insurance Group, Inc."},"rates":{"buy":213.79,"sell":241.23,"timestamp":"2019-01-21 20:49:10"}},
{"stockID":10,"stock":{"industry":"n/a","sector":"n/a","symbol":"BF.B","name":"Brown Forman Corporation"},"rates":{"buy":177.28,"sell":241.31,"timestamp":"2019-12-14 22:17:46"}},
{"stockID":11,"stock":{"industry":"Savings Institutions","sector":"Finance","symbol":"CHFN","name":"Charter Financial Corp."},"rates":{"buy":212.84,"sell":137.74,"timestamp":"2022-07-08 05:55:07"}},
{"stockID":12,"stock":{"industry":"Natural Gas Distribution","sector":"Public Utilities","symbol":"PTXP","name":"PennTex Midstream Partners, LP"},"rates":{"buy":217.05,"sell":250.27,"timestamp":"2021-09-12 14:48:59"}},
{"stockID":13,"stock":{"industry":"Broadcasting","sector":"Consumer Services","symbol":"EMMS","name":"Emmis Communications Corporation"},"rates":{"buy":203.24,"sell":105.53,"timestamp":"2019-10-08 11:33:43"}},
{"stockID":14,"stock":{"industry":"Radio And Television Broadcasting And Communications Equipment","sector":"Technology","symbol":"DCM","name":"NTT DOCOMO, Inc"},"rates":{"buy":121.02,"sell":151.06,"timestamp":"2018-02-18 08:30:45"}},
{"stockID":15,"stock":{"industry":"n/a","sector":"n/a","symbol":"FV","name":"First Trust Dorsey Wright Focus 5 ETF"},"rates":{"buy":132.04,"sell":95.8,"timestamp":"2022-10-06 01:41:05"}},
{"stockID":16,"stock":{"industry":"Investment Managers","sector":"Finance","symbol":"FNGN","name":"Financial Engines, Inc."},"rates":{"buy":241.14,"sell":115.68,"timestamp":"2022-08-23 10:19:19"}},
{"stockID":17,"stock":{"industry":"Biotechnology: Biological Products (No Diagnostic Substances)","sector":"Health Care","symbol":"CYTR","name":"CytRx Corporation"},"rates":{"buy":105.46,"sell":180.74,"timestamp":"2019-11-01 00:28:58"}},
{"stockID":18,"stock":{"industry":"Industrial Machinery/Components","sector":"Technology","symbol":"KAI","name":"Kadant Inc"},"rates":{"buy":186.67,"sell":101.66,"timestamp":"2022-05-26 09:21:03"}},
{"stockID":19,"stock":{"industry":"n/a","sector":"n/a","symbol":"IGOV","name":"iShares S&P/Citigroup International Treasury Bond Fund"},"rates":{"buy":146.38,"sell":140.38,"timestamp":"2021-08-04 05:26:00"}},
{"stockID":20,"stock":{"industry":"Military/Government/Technical","sector":"Consumer Services","symbol":"EGL","name":"Engility Holdings, Inc."},"rates":{"buy":108.45,"sell":265.33,"timestamp":"2018-05-11 00:04:07"}},
{"stockID":21,"stock":{"industry":"Industrial Machinery/Components","sector":"Energy","symbol":"SEV","name":"Sevcon, Inc."},"rates":{"buy":197.69,"sell":248.66,"timestamp":"2020-08-05 02:14:13"}},
{"stockID":22,"stock":{"industry":"RETAIL: Building Materials","sector":"Consumer Services","symbol":"FND","name":"Floor & Decor Holdings, Inc."},"rates":{"buy":241.95,"sell":240.64,"timestamp":"2019-12-15 11:50:30"}},
{"stockID":23,"stock":{"industry":"Packaged Foods","sector":"Consumer Non-Durables","symbol":"PF","name":"Pinnacle Foods, Inc."},"rates":{"buy":126.57,"sell":275.27,"timestamp":"2018-03-18 00:31:08"}},
{"stockID":24,"stock":{"industry":"Department/Specialty Retail Stores","sector":"Consumer Services","symbol":"DDT","name":"Dillard's, Inc."},"rates":{"buy":108.47,"sell":226.24,"timestamp":"2022-04-29 02:34:10"}},
{"stockID":25,"stock":{"industry":"Medical Specialities","sector":"Health Care","symbol":"TRUP","name":"Trupanion, Inc."},"rates":{"buy":124.16,"sell":256.43,"timestamp":"2018-07-25 14:22:43"}},
{"stockID":26,"stock":{"industry":"Property-Casualty Insurers","sector":"Finance","symbol":"GLRE","name":"Greenlight Reinsurance, Ltd."},"rates":{"buy":175.58,"sell":245.54,"timestamp":"2019-02-20 20:08:25"}},
{"stockID":27,"stock":{"industry":"Major Chemicals","sector":"Basic Industries","symbol":"DELTW","name":"Delta Technology Holdings Limited"},"rates":{"buy":145.44,"sell":136.8,"timestamp":"2022-10-06 17:11:18"}},
{"stockID":28,"stock":{"industry":"Specialty Chemicals","sector":"Consumer Durables","symbol":"MTEX","name":"Mannatech, Incorporated"},"rates":{"buy":139.2,"sell":224.02,"timestamp":"2019-02-25 15:29:53"}},
{"stockID":29,"stock":{"industry":"Consumer Electronics/Appliances","sector":"Consumer Durables","symbol":"WHR","name":"Whirlpool Corporation"},"rates":{"buy":221.06,"sell":189.2,"timestamp":"2021-02-22 02:37:30"}},
{"stockID":30,"stock":{"industry":"Major Banks","sector":"Finance","symbol":"WSFS","name":"WSFS Financial Corporation"},"rates":{"buy":126.11,"sell":187.06,"timestamp":"2021-11-14 21:42:19"}},
{"stockID":31,"stock":{"industry":"n/a","sector":"n/a","symbol":"NTG","name":"Tortoise MLP Fund, Inc."},"rates":{"buy":196.19,"sell":130.22,"timestamp":"2019-01-23 17:31:34"}},
{"stockID":32,"stock":{"industry":"n/a","sector":"n/a","symbol":"DUC","name":"Duff & Phelps Utility & Corporate Bond Trust, Inc."},"rates":{"buy":192.48,"sell":147.44,"timestamp":"2021-05-08 23:31:16"}},
{"stockID":33,"stock":{"industry":"n/a","sector":"n/a","symbol":"JMM","name":"Nuveen Multi-Market Income Fund"},"rates":{"buy":149.89,"sell":140.98,"timestamp":"2018-03-10 05:04:52"}},
{"stockID":34,"stock":{"industry":"Property-Casualty Insurers","sector":"Finance","symbol":"XL","name":"XL Group Ltd."},"rates":{"buy":169.24,"sell":88.96,"timestamp":"2022-01-22 07:45:53"}},
{"stockID":35,"stock":{"industry":"Newspapers/Magazines","sector":"Consumer Services","symbol":"TST","name":"TheStreet, Inc."},"rates":{"buy":194.21,"sell":137.34,"timestamp":"2019-07-21 19:59:08"}},
{"stockID":36,"stock":{"industry":"n/a","sector":"n/a","symbol":"VONV","name":"Vanguard Russell 1000 Value ETF"},"rates":{"buy":157.87,"sell":225.98,"timestamp":"2019-06-06 10:48:15"}},
{"stockID":37,"stock":{"industry":"Other Specialty Stores","sector":"Consumer Services","symbol":"ZAGG","name":"ZAGG Inc"},"rates":{"buy":212.02,"sell":176.87,"timestamp":"2018-03-26 12:22:31"}},
{"stockID":38,"stock":{"industry":"Food Distributors","sector":"Consumer Non-Durables","symbol":"WILC","name":"G. Willi-Food International,  Ltd."},"rates":{"buy":190.83,"sell":207.95,"timestamp":"2020-07-05 15:41:32"}},
{"stockID":39,"stock":{"industry":"n/a","sector":"n/a","symbol":"VSDA","name":"VictoryShares Dividend Accelerator ETF"},"rates":{"buy":112.2,"sell":96.27,"timestamp":"2022-05-08 07:19:58"}},
{"stockID":40,"stock":{"industry":"EDP Services","sector":"Technology","symbol":"SPRT","name":"support.com, Inc."},"rates":{"buy":247.45,"sell":228.73,"timestamp":"2018-02-19 08:10:17"}},
{"stockID":41,"stock":{"industry":"Other Consumer Services","sector":"Consumer Services","symbol":"EDU","name":"New Oriental Education & Technology Group, Inc."},"rates":{"buy":133.5,"sell":241.44,"timestamp":"2021-11-20 09:50:12"}},
{"stockID":42,"stock":{"industry":"Real Estate Investment Trusts","sector":"Consumer Services","symbol":"KRC","name":"Kilroy Realty Corporation"},"rates":{"buy":169.55,"sell":266.76,"timestamp":"2022-12-13 04:29:48"}},
{"stockID":43,"stock":{"industry":"Major Banks","sector":"Finance","symbol":"PVTBP","name":"PrivateBancorp, Inc."},"rates":{"buy":128.23,"sell":117.23,"timestamp":"2022-09-01 01:03:31"}},
{"stockID":44,"stock":{"industry":"Business Services","sector":"Miscellaneous","symbol":"QPACW","name":"Quinpario Acquisition Corp. 2"},"rates":{"buy":215.27,"sell":110.67,"timestamp":"2020-02-05 17:50:13"}},
{"stockID":45,"stock":{"industry":"n/a","sector":"n/a","symbol":"KMF","name":"Kayne Anderson Midstream Energy Fund, Inc"},"rates":{"buy":168.52,"sell":149.21,"timestamp":"2020-11-20 05:42:07"}},
{"stockID":46,"stock":{"industry":"Industrial Machinery/Components","sector":"Capital Goods","symbol":"SWP","name":"Stanley Black & Decker, Inc."},"rates":{"buy":246.98,"sell":275.46,"timestamp":"2022-07-08 01:33:47"}},
{"stockID":47,"stock":{"industry":"n/a","sector":"n/a","symbol":"HPS","name":"John Hancock Preferred Income Fund III"},"rates":{"buy":154.29,"sell":258.21,"timestamp":"2019-06-25 22:10:52"}},
{"stockID":48,"stock":{"industry":"Major Pharmaceuticals","sector":"Health Care","symbol":"CRME","name":"Cardiome Pharma Corporation"},"rates":{"buy":154.58,"sell":267.43,"timestamp":"2018-07-19 23:42:14"}},
{"stockID":49,"stock":{"industry":"Beverages (Production/Distribution)","sector":"Consumer Non-Durables","symbol":"KOF","name":"Coca Cola Femsa S.A.B. de C.V."},"rates":{"buy":122.15,"sell":225.37,"timestamp":"2018-06-18 15:10:58"}},
{"stockID":50,"stock":{"industry":"Major Banks","sector":"Finance","symbol":"BPOPN","name":"Popular, Inc."},"rates":{"buy":167.91,"sell":248.27,"timestamp":"2018-01-08 00:40:05"}},
{"stockID":51,"stock":{"industry":"Real Estate Investment Trusts","sector":"Consumer Services","symbol":"FCPT","name":"Four Corners Property Trust, Inc."},"rates":{"buy":179.02,"sell":144.65,"timestamp":"2020-03-06 09:16:34"}},
{"stockID":52,"stock":{"industry":"Marine Transportation","sector":"Transportation","symbol":"SALT","name":"Scorpio Bulkers Inc."},"rates":{"buy":229.18,"sell":198.64,"timestamp":"2020-01-29 02:50:10"}},
{"stockID":53,"stock":{"industry":"Medical Specialities","sector":"Health Care","symbol":"OPGN","name":"OpGen, Inc."},"rates":{"buy":112.97,"sell":246.52,"timestamp":"2018-10-12 04:24:18"}},
{"stockID":54,"stock":{"industry":"Medical Specialities","sector":"Health Care","symbol":"VCYT","name":"Veracyte, Inc."},"rates":{"buy":103.62,"sell":236.04,"timestamp":"2022-06-08 09:55:34"}},
{"stockID":55,"stock":{"industry":"Business Services","sector":"Finance","symbol":"OACQR","name":"Origo Acquisition Corporation"},"rates":{"buy":154.44,"sell":90.94,"timestamp":"2021-11-15 20:18:58"}},
{"stockID":56,"stock":{"industry":"Semiconductors","sector":"Technology","symbol":"IMI","name":"Intermolecular, Inc."},"rates":{"buy":208.72,"sell":138.58,"timestamp":"2022-04-20 08:20:11"}},
{"stockID":57,"stock":{"industry":"Industrial Machinery/Components","sector":"Technology","symbol":"CVV","name":"CVD Equipment Corporation"},"rates":{"buy":247.76,"sell":184.67,"timestamp":"2021-01-31 10:25:23"}},
{"stockID":58,"stock":{"industry":"Clothing/Shoe/Accessory Stores","sector":"Consumer Services","symbol":"SSI","name":"Stage Stores, Inc."},"rates":{"buy":192.53,"sell":186.07,"timestamp":"2022-02-22 18:42:53"}},
{"stockID":59,"stock":{"industry":"Industrial Machinery/Components","sector":"Energy","symbol":"WPRT","name":"Westport Fuel Systems Inc"},"rates":{"buy":205.96,"sell":126.51,"timestamp":"2018-05-09 12:28:54"}},
{"stockID":60,"stock":{"industry":"Building Materials","sector":"Capital Goods","symbol":"JHX","name":"James Hardie Industries plc."},"rates":{"buy":122.76,"sell":170.01,"timestamp":"2019-11-02 03:52:28"}},
{"stockID":61,"stock":{"industry":"Other Consumer Services","sector":"Consumer Services","symbol":"NAUH","name":"National American University Holdings, Inc."},"rates":{"buy":214.1,"sell":172.65,"timestamp":"2021-01-14 14:31:31"}},
{"stockID":62,"stock":{"industry":"Telecommunications Equipment","sector":"Public Utilities","symbol":"AMOV","name":"America Movil, S.A.B. de C.V."},"rates":{"buy":110.45,"sell":235.21,"timestamp":"2022-07-10 13:08:08"}},
{"stockID":63,"stock":{"industry":"Major Banks","sector":"Finance","symbol":"SIVB","name":"SVB Financial Group"},"rates":{"buy":201.13,"sell":96.1,"timestamp":"2020-10-05 00:58:12"}},
{"stockID":64,"stock":{"industry":"Major Pharmaceuticals","sector":"Health Care","symbol":"KALV","name":"KalVista Pharmaceuticals, Inc."},"rates":{"buy":194.19,"sell":118.88,"timestamp":"2021-12-05 13:26:43"}},
{"stockID":65,"stock":{"industry":"n/a","sector":"n/a","symbol":"SRF","name":"Cushing Energy Income Fund (The)"},"rates":{"buy":234.16,"sell":123.13,"timestamp":"2022-02-19 22:31:28"}},
{"stockID":66,"stock":{"industry":"n/a","sector":"n/a","symbol":"NEWT","name":"Newtek Business Services Corp."},"rates":{"buy":157.3,"sell":174.7,"timestamp":"2022-04-08 17:09:15"}},
{"stockID":67,"stock":{"industry":"n/a","sector":"n/a","symbol":"UBND","name":"WisdomTree Western Asset Unconstrained Bond Fund"},"rates":{"buy":115.29,"sell":204.8,"timestamp":"2022-09-19 22:33:49"}},
{"stockID":68,"stock":{"industry":"n/a","sector":"n/a","symbol":"CHN","name":"China Fund, Inc. (The)"},"rates":{"buy":222.61,"sell":253.6,"timestamp":"2022-02-08 09:31:23"}},
{"stockID":69,"stock":{"industry":"Biotechnology: Biological Products (No Diagnostic Substances)","sector":"Health Care","symbol":"ONCE","name":"Spark Therapeutics, Inc."},"rates":{"buy":206.9,"sell":223.55,"timestamp":"2022-05-04 12:20:41"}},
{"stockID":70,"stock":{"industry":"n/a","sector":"n/a","symbol":"GDV^A","name":"Gabelli Dividend"},"rates":{"buy":204.57,"sell":112.78,"timestamp":"2021-04-10 01:05:18"}},
{"stockID":71,"stock":{"industry":"Computer peripheral equipment","sector":"Technology","symbol":"MITK","name":"Mitek Systems, Inc."},"rates":{"buy":233.1,"sell":235.19,"timestamp":"2022-06-10 21:52:08"}},
{"stockID":72,"stock":{"industry":"Biotechnology: In Vitro & In Vivo Diagnostic Substances","sector":"Health Care","symbol":"OGXI","name":"OncoGenex Pharmaceuticals Inc."},"rates":{"buy":146.72,"sell":123.54,"timestamp":"2020-07-10 09:05:25"}},
{"stockID":73,"stock":{"industry":"Air Freight/Delivery Services","sector":"Transportation","symbol":"ALGT","name":"Allegiant Travel Company"},"rates":{"buy":171.78,"sell":99.03,"timestamp":"2021-07-13 09:06:11"}},
{"stockID":74,"stock":{"industry":"n/a","sector":"n/a","symbol":"INFR","name":"Legg Mason Global Infrastructure ETF"},"rates":{"buy":221.24,"sell":230.93,"timestamp":"2018-07-17 15:17:28"}},
{"stockID":75,"stock":{"industry":"Real Estate Investment Trusts","sector":"Consumer Services","symbol":"GEO","name":"Geo Group Inc (The)"},"rates":{"buy":192.01,"sell":255.33,"timestamp":"2022-07-09 12:16:08"}},
{"stockID":76,"stock":{"industry":"n/a","sector":"n/a","symbol":"FTHI","name":"First Trust High Income ETF"},"rates":{"buy":187.54,"sell":164.88,"timestamp":"2021-02-12 06:09:18"}},
{"stockID":77,"stock":{"industry":"Major Pharmaceuticals","sector":"Health Care","symbol":"RXIIW","name":"RXi Pharmaceuticals Corporation"},"rates":{"buy":239.02,"sell":228.7,"timestamp":"2021-03-26 15:42:54"}},
{"stockID":78,"stock":{"industry":"Industrial Machinery/Components","sector":"Technology","symbol":"JBT","name":"John Bean Technologies Corporation"},"rates":{"buy":184.95,"sell":233.25,"timestamp":"2021-05-08 14:54:45"}},
{"stockID":79,"stock":{"industry":"Major Banks","sector":"Finance","symbol":"FHN","name":"First Horizon National Corporation"},"rates":{"buy":146.16,"sell":250.47,"timestamp":"2021-01-29 17:36:52"}},
{"stockID":80,"stock":{"industry":"Industrial Machinery/Components","sector":"Technology","symbol":"KTEC","name":"Key Technology, Inc."},"rates":{"buy":123.67,"sell":158.04,"timestamp":"2021-12-08 03:41:01"}},
{"stockID":81,"stock":{"industry":"Radio And Television Broadcasting And Communications Equipment","sector":"Technology","symbol":"ARRS","name":"ARRIS International plc"},"rates":{"buy":108.42,"sell":138.13,"timestamp":"2022-08-28 08:02:10"}},
{"stockID":82,"stock":{"industry":"Clothing/Shoe/Accessory Stores","sector":"Consumer Services","symbol":"CTRN","name":"Citi Trends, Inc."},"rates":{"buy":200.23,"sell":156.81,"timestamp":"2022-04-21 21:47:39"}},
{"stockID":83,"stock":{"industry":"Semiconductors","sector":"Technology","symbol":"RBCN","name":"Rubicon Technology, Inc."},"rates":{"buy":160.42,"sell":238.92,"timestamp":"2018-06-26 11:40:57"}},
{"stockID":84,"stock":{"industry":"Consumer Electronics/Appliances","sector":"Energy","symbol":"EMR","name":"Emerson Electric Company"},"rates":{"buy":202.08,"sell":276.76,"timestamp":"2019-04-16 14:32:04"}},
{"stockID":85,"stock":{"industry":"n/a","sector":"n/a","symbol":"OXLC","name":"Oxford Lane Capital Corp."},"rates":{"buy":197.53,"sell":277.7,"timestamp":"2022-02-09 14:53:22"}},
{"stockID":86,"stock":{"industry":"Other Specialty Stores","sector":"Consumer Services","symbol":"ORLY","name":"O'Reilly Automotive, Inc."},"rates":{"buy":226.01,"sell":146.34,"timestamp":"2021-09-10 11:11:11"}},
{"stockID":87,"stock":{"industry":"Oil & Gas Production","sector":"Energy","symbol":"MARPS","name":"Marine Petroleum Trust"},"rates":{"buy":234.42,"sell":217.38,"timestamp":"2018-05-14 03:49:44"}},
{"stockID":88,"stock":{"industry":"Environmental Services","sector":"Consumer Non-Durables","symbol":"POPE","name":"Pope Resources"},"rates":{"buy":172.02,"sell":216.38,"timestamp":"2019-10-18 16:32:51"}},
{"stockID":89,"stock":{"industry":"Automotive Aftermarket","sector":"Consumer Durables","symbol":"LAD","name":"Lithia Motors, Inc."},"rates":{"buy":191.79,"sell":245.21,"timestamp":"2021-01-03 20:14:30"}},
{"stockID":90,"stock":{"industry":"Telecommunications Equipment","sector":"Consumer Durables","symbol":"MAGS","name":"Magal Security Systems Ltd."},"rates":{"buy":233.92,"sell":167.62,"timestamp":"2018-06-20 06:47:25"}},
{"stockID":91,"stock":{"industry":"Natural Gas Distribution","sector":"Energy","symbol":"VLP","name":"Valero Energy Partners LP"},"rates":{"buy":148.27,"sell":268.75,"timestamp":"2020-09-09 08:59:33"}},
{"stockID":92,"stock":{"industry":"Major Banks","sector":"Finance","symbol":"SMMF","name":"Summit Financial Group, Inc."},"rates":{"buy":146.58,"sell":137.33,"timestamp":"2018-09-03 19:17:30"}},
{"stockID":93,"stock":{"industry":"Homebuilding","sector":"Capital Goods","symbol":"NVR","name":"NVR, Inc."},"rates":{"buy":213.15,"sell":111.3,"timestamp":"2020-10-14 21:04:52"}},
{"stockID":94,"stock":{"industry":"Major Banks","sector":"Finance","symbol":"EBTC","name":"Enterprise Bancorp Inc"},"rates":{"buy":112.6,"sell":163.54,"timestamp":"2018-04-27 10:19:13"}},
{"stockID":95,"stock":{"industry":"Telecommunications Equipment","sector":"Consumer Services","symbol":"ORBC","name":"ORBCOMM Inc."},"rates":{"buy":181.29,"sell":252.71,"timestamp":"2022-04-21 04:08:30"}},
{"stockID":96,"stock":{"industry":"Computer peripheral equipment","sector":"Technology","symbol":"INVE","name":"Identiv, Inc."},"rates":{"buy":235.08,"sell":277.11,"timestamp":"2021-05-16 17:28:34"}},
{"stockID":97,"stock":{"industry":"n/a","sector":"n/a","symbol":"FPF","name":"First Trust Intermediate Duration Preferred & Income Fund"},"rates":{"buy":153.6,"sell":122.71,"timestamp":"2020-04-03 00:57:50"}},
{"stockID":98,"stock":{"industry":"n/a","sector":"n/a","symbol":"NEWTL","name":"Newtek Business Services Corp."},"rates":{"buy":209.53,"sell":261.56,"timestamp":"2021-12-02 09:02:55"}},
{"stockID":99,"stock":{"industry":"Major Pharmaceuticals","sector":"Health Care","symbol":"SNSS","name":"Sunesis Pharmaceuticals, Inc."},"rates":{"buy":132.39,"sell":81.37,"timestamp":"2020-05-28 15:24:23"}},
{"stockID":100,"stock":{"industry":"Building Materials","sector":"Capital Goods","symbol":"CX","name":"Cemex S.A.B. de C.V."},"rates":{"buy":118.75,"sell":172.46,"timestamp":"2022-10-01 06:55:52"}},
{"stockID":101,"stock":{"industry":"Advertising","sector":"Technology","symbol":"GRPN","name":"Groupon, Inc."},"rates":{"buy":141.03,"sell":124.8,"timestamp":"2018-03-21 12:09:10"}},
{"stockID":102,"stock":{"industry":"Department/Specialty Retail Stores","sector":"Consumer Services","symbol":"TUES","name":"Tuesday Morning Corp."},"rates":{"buy":132.59,"sell":131.0,"timestamp":"2020-12-03 11:45:27"}},
{"stockID":103,"stock":{"industry":"Military/Government/Technical","sector":"Capital Goods","symbol":"AJRD","name":"Aerojet Rocketdyne Holdings, Inc. "},"rates":{"buy":111.55,"sell":218.19,"timestamp":"2021-08-14 16:12:51"}},
{"stockID":104,"stock":{"industry":"n/a","sector":"n/a","symbol":"FEM","name":"First Trust Emerging Markets AlphaDEX Fund"},"rates":{"buy":196.56,"sell":96.76,"timestamp":"2022-10-24 07:02:20"}},
{"stockID":105,"stock":{"industry":"n/a","sector":"n/a","symbol":"VGLT","name":"Vanguard Long-Term Government Bond ETF"},"rates":{"buy":108.78,"sell":144.28,"timestamp":"2022-12-20 11:19:24"}},
{"stockID":106,"stock":{"industry":"Oil & Gas Production","sector":"Energy","symbol":"HESM","name":"Hess Midstream Partners LP"},"rates":{"buy":219.44,"sell":200.98,"timestamp":"2019-06-10 13:33:23"}},
{"stockID":107,"stock":{"industry":"n/a","sector":"n/a","symbol":"JLS","name":"Nuveen Mortgage Opportunity Term Fund"},"rates":{"buy":108.4,"sell":260.52,"timestamp":"2020-03-15 08:56:45"}},
{"stockID":108,"stock":{"industry":"Other Consumer Services","sector":"Consumer Services","symbol":"LOPE","name":"Grand Canyon Education, Inc."},"rates":{"buy":206.37,"sell":208.89,"timestamp":"2021-11-28 16:50:32"}},
{"stockID":109,"stock":{"industry":"Newspapers/Magazines","sector":"Consumer Services","symbol":"AXR","name":"AMREP Corporation"},"rates":{"buy":232.35,"sell":258.23,"timestamp":"2020-01-27 05:32:22"}},
{"stockID":110,"stock":{"industry":"Metal Fabrications","sector":"Consumer Durables","symbol":"AMSC","name":"American Superconductor Corporation"},"rates":{"buy":193.29,"sell":229.79,"timestamp":"2018-03-22 01:41:40"}}]}